[{"human":"http://www.wikidata.org/entity/Q544465","humanLabel":"Kathy Bates","image":"http://commons.wikimedia.org/wiki/Special:FilePath/Kathy%20Bates%202006.jpg","sex_or_gender":"http://www.wikidata.org/entity/Q6581072","sex_or_genderLabel":"female"},{"human":"http://www.wikidata.org/entity/Q1033016","humanLabel":"Halle Berry","image":"http://commons.wikimedia.org/wiki/Special:FilePath/Halle%20Berry%20by%20Gage%20Skidmore%202.jpg","sex_or_gender":"http://www.wikidata.org/entity/Q6581072","sex_or_genderLabel":"female"},{"human":"http://www.wikidata.org/entity/Q1111542","humanLabel":"Joanne Woodward","image":"http://commons.wikimedia.org/wiki/Special:FilePath/Joanne%20Woodward%201960.JPG","sex_or_gender":"http://www.wikidata.org/entity/Q6581072","sex_or_genderLabel":"female"},{"human":"http://www.wikidata.org/entity/Q873","humanLabel":"Meryl Streep","image":"http://commons.wikimedia.org/wiki/Special:FilePath/Meryl%20Streep%20at%20the%20Tokyo%20International%20Film%20Festival%202016%20%2832801846044%29%20%28cropped%29.jpg","sex_or_gender":"http://www.wikidata.org/entity/Q6581072","sex_or_genderLabel":"female"},{"human":"http://www.wikidata.org/entity/Q3925","humanLabel":"Grace Kelly","image":"http://commons.wikimedia.org/wiki/Special:FilePath/To%20Catch%20a%20Thief1.jpg","sex_or_gender":"http://www.wikidata.org/entity/Q6581072","sex_or_genderLabel":"female"},{"human":"http://www.wikidata.org/entity/Q8927","humanLabel":"Marion Cotillard","image":"http://commons.wikimedia.org/wiki/Special:FilePath/Marion%20Cotillard%20Cabourg%202017.jpg","sex_or_gender":"http://www.wikidata.org/entity/Q6581072","sex_or_genderLabel":"female"},{"human":"http://www.wikidata.org/entity/Q12003","humanLabel":"Cher","image":"http://commons.wikimedia.org/wiki/Special:FilePath/Cher%20by%20Ian%20Smith.jpg","sex_or_gender":"http://www.wikidata.org/entity/Q6581072","sex_or_genderLabel":"female"},{"human":"http://www.wikidata.org/entity/Q29328","humanLabel":"Brie Larson","image":"http://commons.wikimedia.org/wiki/Special:FilePath/Brie%20Larson%20in%202017.jpeg","sex_or_gender":"http://www.wikidata.org/entity/Q6581072","sex_or_genderLabel":"female"},{"human":"http://www.wikidata.org/entity/Q34851","humanLabel":"Elizabeth Taylor","image":"http://commons.wikimedia.org/wiki/Special:FilePath/Taylor%2C%20Elizabeth%20posed.jpg","sex_or_gender":"http://www.wikidata.org/entity/Q6581072","sex_or_genderLabel":"female"},{"human":"http://www.wikidata.org/entity/Q37459","humanLabel":"Nicole Kidman","image":"http://commons.wikimedia.org/wiki/Special:FilePath/Nicole%20Kidman%203%2C%202012.jpg","sex_or_gender":"http://www.wikidata.org/entity/Q6581072","sex_or_genderLabel":"female"},{"human":"http://www.wikidata.org/entity/Q40475","humanLabel":"Joan Crawford","image":"http://commons.wikimedia.org/wiki/Special:FilePath/Joan%20Crawford%20-%201936%20-%20Hurrell.JPG","sex_or_gender":"http://www.wikidata.org/entity/Q6581072","sex_or_genderLabel":"female"},{"human":"http://www.wikidata.org/entity/Q40791","humanLabel":"Sandra Bullock","image":"http://commons.wikimedia.org/wiki/Special:FilePath/Sandra%20Bullock%202011%20AA.jpg","sex_or_gender":"http://www.wikidata.org/entity/Q6581072","sex_or_genderLabel":"female"},{"human":"http://www.wikidata.org/entity/Q41142","humanLabel":"Jane Fonda","image":"http://commons.wikimedia.org/wiki/Special:FilePath/Jane%20Fonda%20Cannes%202014.jpg","sex_or_gender":"http://www.wikidata.org/entity/Q6581072","sex_or_genderLabel":"female"},{"human":"http://www.wikidata.org/entity/Q41351","humanLabel":"Jodie Foster","image":"http://commons.wikimedia.org/wiki/Special:FilePath/Jodie%20Foster%20C%C3%A9sars%202011%202%20%28cropped%29.jpg","sex_or_gender":"http://www.wikidata.org/entity/Q6581072","sex_or_genderLabel":"female"},{"human":"http://www.wikidata.org/entity/Q42786","humanLabel":"Audrey Hepburn","image":"http://commons.wikimedia.org/wiki/Special:FilePath/Audrey%20Hepburn%201956.jpg","sex_or_gender":"http://www.wikidata.org/entity/Q6581072","sex_or_genderLabel":"female"},{"human":"http://www.wikidata.org/entity/Q43247","humanLabel":"Ingrid Bergman","image":"http://commons.wikimedia.org/wiki/Special:FilePath/Ingrid%20Bergman%20The%20Constant%20Wife%201975.JPG","sex_or_gender":"http://www.wikidata.org/entity/Q6581072","sex_or_genderLabel":"female"},{"human":"http://www.wikidata.org/entity/Q43252","humanLabel":"Sophia Loren","image":"http://commons.wikimedia.org/wiki/Special:FilePath/Sophia%20Loren%20-%201955.JPG","sex_or_gender":"http://www.wikidata.org/entity/Q6581072","sex_or_genderLabel":"female"},{"human":"http://www.wikidata.org/entity/Q44063","humanLabel":"Reese Witherspoon","image":"http://commons.wikimedia.org/wiki/Special:FilePath/Sing%2028%20%2829144392254%29.jpg","sex_or_gender":"http://www.wikidata.org/entity/Q6581072","sex_or_genderLabel":"female"},{"human":"http://www.wikidata.org/entity/Q56011","humanLabel":"Anna Magnani","image":"http://commons.wikimedia.org/wiki/Special:FilePath/Anna%20Magnani-signed.jpg","sex_or_gender":"http://www.wikidata.org/entity/Q6581072","sex_or_genderLabel":"female"},{"human":"http://www.wikidata.org/entity/Q56016","humanLabel":"Katharine Hepburn","image":"http://commons.wikimedia.org/wiki/Special:FilePath/Katharine%20Hepburn%20promo%20pic.jpg","sex_or_gender":"http://www.wikidata.org/entity/Q6581072","sex_or_genderLabel":"female"},{"human":"http://www.wikidata.org/entity/Q71206","humanLabel":"Bette Davis","image":"http://commons.wikimedia.org/wiki/Special:FilePath/Bette%20Davis%20-%20portrait.jpg","sex_or_gender":"http://www.wikidata.org/entity/Q6581072","sex_or_genderLabel":"female"},{"human":"http://www.wikidata.org/entity/Q80046","humanLabel":"Charlize Theron","image":"http://commons.wikimedia.org/wiki/Special:FilePath/Charlize-theron-IMG%206045.jpg","sex_or_gender":"http://www.wikidata.org/entity/Q6581072","sex_or_genderLabel":"female"},{"human":"http://www.wikidata.org/entity/Q80966","humanLabel":"Cate Blanchett","image":"http://commons.wikimedia.org/wiki/Special:FilePath/Cate%20Blanchett%20SDCC%202014%20%28cropped%29.jpg","sex_or_gender":"http://www.wikidata.org/entity/Q6581072","sex_or_genderLabel":"female"},{"human":"http://www.wikidata.org/entity/Q93187","humanLabel":"Hilary Swank","image":"http://commons.wikimedia.org/wiki/Special:FilePath/Hilary%20Swank%20Life%20Ball%202013.jpg","sex_or_gender":"http://www.wikidata.org/entity/Q6581072","sex_or_genderLabel":"female"},{"human":"http://www.wikidata.org/entity/Q95019","humanLabel":"Norma Shearer","image":"http://commons.wikimedia.org/wiki/Special:FilePath/RH%20Louise%20Norma%20Shearer.png","sex_or_gender":"http://www.wikidata.org/entity/Q6581072","sex_or_genderLabel":"female"},{"human":"http://www.wikidata.org/entity/Q95026","humanLabel":"Shirley MacLaine","image":"http://commons.wikimedia.org/wiki/Special:FilePath/Shirley%20MacLaine18.JPG","sex_or_gender":"http://www.wikidata.org/entity/Q6581072","sex_or_genderLabel":"female"},{"human":"http://www.wikidata.org/entity/Q95055","humanLabel":"Jane Wyman","image":"http://commons.wikimedia.org/wiki/Special:FilePath/Promotional%20photograph%20of%20Jane%20Wyman.jpg","sex_or_gender":"http://www.wikidata.org/entity/Q6581072","sex_or_genderLabel":"female"},{"human":"http://www.wikidata.org/entity/Q95068","humanLabel":"Olivia de Havilland","image":"http://commons.wikimedia.org/wiki/Special:FilePath/Santa%20Fe%20Trail%203.jpg","sex_or_gender":"http://www.wikidata.org/entity/Q6581072","sex_or_genderLabel":"female"},{"human":"http://www.wikidata.org/entity/Q95076","humanLabel":"Joan Fontaine","image":"http://commons.wikimedia.org/wiki/Special:FilePath/Joan%20Fontaine%201943.jpg","sex_or_gender":"http://www.wikidata.org/entity/Q6581072","sex_or_genderLabel":"female"},{"human":"http://www.wikidata.org/entity/Q95089","humanLabel":"Ginger Rogers","image":"http://commons.wikimedia.org/wiki/Special:FilePath/Ginger%20Rogers%20-%201940s.jpg","sex_or_gender":"http://www.wikidata.org/entity/Q6581072","sex_or_genderLabel":"female"},{"human":"http://www.wikidata.org/entity/Q104109","humanLabel":"Mary Pickford","image":"http://commons.wikimedia.org/wiki/Special:FilePath/Mary%20Pickford%20cph.3c17995u.jpg","sex_or_gender":"http://www.wikidata.org/entity/Q6581072","sex_or_genderLabel":"female"},{"human":"http://www.wikidata.org/entity/Q105660","humanLabel":"Holly Hunter","image":"http://commons.wikimedia.org/wiki/Special:FilePath/HollyHunter.jpg","sex_or_gender":"http://www.wikidata.org/entity/Q6581072","sex_or_genderLabel":"female"},{"human":"http://www.wikidata.org/entity/Q106126","humanLabel":"Simone Signoret","image":"http://commons.wikimedia.org/wiki/Special:FilePath/Simone%20Signoret.jpg","sex_or_gender":"http://www.wikidata.org/entity/Q6581072","sex_or_genderLabel":"female"},{"human":"http://www.wikidata.org/entity/Q129429","humanLabel":"Vivien Leigh","image":"http://commons.wikimedia.org/wiki/Special:FilePath/Vivien%20Leigh%20Scarlet.jpg","sex_or_gender":"http://www.wikidata.org/entity/Q6581072","sex_or_genderLabel":"female"},{"human":"http://www.wikidata.org/entity/Q133050","humanLabel":"Susan Sarandon","image":"http://commons.wikimedia.org/wiki/Special:FilePath/Susan%20Sarandon%2C%20Festival%20de%20Sitges%202017.jpg","sex_or_gender":"http://www.wikidata.org/entity/Q6581072","sex_or_genderLabel":"female"},{"human":"http://www.wikidata.org/entity/Q147077","humanLabel":"Emma Stone","image":"http://commons.wikimedia.org/wiki/Special:FilePath/Emma%20Stone%20at%20Battle%20of%20the%20Sexes%2C%20London%20%2837526182652%29%20%28cropped%29.jpg","sex_or_gender":"http://www.wikidata.org/entity/Q6581072","sex_or_genderLabel":"female"},{"human":"http://www.wikidata.org/entity/Q161819","humanLabel":"Julie Andrews","image":"http://commons.wikimedia.org/wiki/Special:FilePath/Julie%20Andrews%20Park%20Hyatt%2C%20Sydney%2C%20Australia%202013.jpg","sex_or_gender":"http://www.wikidata.org/entity/Q6581072","sex_or_genderLabel":"female"},{"human":"http://www.wikidata.org/entity/Q168721","humanLabel":"Faye Dunaway","image":"http://commons.wikimedia.org/wiki/Special:FilePath/Faye%20Dunaway%20-%201971%20-%20PBS.JPG","sex_or_gender":"http://www.wikidata.org/entity/Q6581072","sex_or_genderLabel":"female"},{"human":"http://www.wikidata.org/entity/Q168724","humanLabel":"Emma Thompson","image":"http://commons.wikimedia.org/wiki/Special:FilePath/Emma%20Thompson%20C%C3%A9sars%202009.jpg","sex_or_gender":"http://www.wikidata.org/entity/Q6581072","sex_or_genderLabel":"female"},{"human":"http://www.wikidata.org/entity/Q170574","humanLabel":"Helen Hunt","image":"http://commons.wikimedia.org/wiki/Special:FilePath/HelenHunt%40ambiente2015.JPG","sex_or_gender":"http://www.wikidata.org/entity/Q6581072","sex_or_genderLabel":"female"},{"human":"http://www.wikidata.org/entity/Q181413","humanLabel":"Julie Christie","image":"http://commons.wikimedia.org/wiki/Special:FilePath/Julie%20Christie%20-%201966.jpg","sex_or_gender":"http://www.wikidata.org/entity/Q6581072","sex_or_genderLabel":"female"},{"human":"http://www.wikidata.org/entity/Q182372","humanLabel":"Louise Fletcher","image":"http://commons.wikimedia.org/wiki/Special:FilePath/Louise%20Fletcher%20cropp.jpg","sex_or_gender":"http://www.wikidata.org/entity/Q6581072","sex_or_genderLabel":"female"},{"human":"http://www.wikidata.org/entity/Q182486","humanLabel":"Greer Garson","image":"http://commons.wikimedia.org/wiki/Special:FilePath/Greer%20Garson-publicity.JPG","sex_or_gender":"http://www.wikidata.org/entity/Q6581072","sex_or_genderLabel":"female"},{"human":"http://www.wikidata.org/entity/Q187033","humanLabel":"Sally Field","image":"http://commons.wikimedia.org/wiki/Special:FilePath/Sally%20Field%201971%20%28cropped%29.jpg","sex_or_gender":"http://www.wikidata.org/entity/Q6581072","sex_or_genderLabel":"female"},{"human":"http://www.wikidata.org/entity/Q189490","humanLabel":"Jennifer Lawrence","image":"http://commons.wikimedia.org/wiki/Special:FilePath/Jennifer%20Lawrence%20SDCC%202015%20X-Men.jpg","sex_or_gender":"http://www.wikidata.org/entity/Q6581072","sex_or_genderLabel":"female"},{"human":"http://www.wikidata.org/entity/Q189895","humanLabel":"Jennifer Jones","image":"http://commons.wikimedia.org/wiki/Special:FilePath/Jennifer%20Jones%20-%20Publicity.JPG","sex_or_gender":"http://www.wikidata.org/entity/Q6581072","sex_or_genderLabel":"female"},{"human":"http://www.wikidata.org/entity/Q190994","humanLabel":"Sissy Spacek","image":"http://commons.wikimedia.org/wiki/Special:FilePath/SissySpacekHSHWOFAug2011.jpg","sex_or_gender":"http://www.wikidata.org/entity/Q6581072","sex_or_genderLabel":"female"},{"human":"http://www.wikidata.org/entity/Q191027","humanLabel":"Patricia Neal","image":"http://commons.wikimedia.org/wiki/Special:FilePath/Patricia%20Neal%201952.JPG","sex_or_gender":"http://www.wikidata.org/entity/Q6581072","sex_or_genderLabel":"female"},{"human":"http://www.wikidata.org/entity/Q202765","humanLabel":"Kate Winslet","image":"http://commons.wikimedia.org/wiki/Special:FilePath/KateWinsletByAndreaRaffin2011.jpg","sex_or_gender":"http://www.wikidata.org/entity/Q6581072","sex_or_genderLabel":"female"},{"human":"http://www.wikidata.org/entity/Q204299","humanLabel":"Frances McDormand","image":"http://commons.wikimedia.org/wiki/Special:FilePath/Frances%20McDormand%202015%20%28cropped%29.jpg","sex_or_gender":"http://www.wikidata.org/entity/Q6581072","sex_or_genderLabel":"female"},{"human":"http://www.wikidata.org/entity/Q211144","humanLabel":"Ellen Burstyn","image":"http://commons.wikimedia.org/wiki/Special:FilePath/Ellen%20Burstyn%20at%20the%202009%20Tribeca%20Film%20Festival.jpg","sex_or_gender":"http://www.wikidata.org/entity/Q6581072","sex_or_genderLabel":"female"},{"human":"http://www.wikidata.org/entity/Q213287","humanLabel":"Marlee Matlin","image":"http://commons.wikimedia.org/wiki/Special:FilePath/MarleeMatlinMay09.jpg","sex_or_gender":"http://www.wikidata.org/entity/Q6581072","sex_or_genderLabel":"female"},{"human":"http://www.wikidata.org/entity/Q213302","humanLabel":"Helen Hayes","image":"http://commons.wikimedia.org/wiki/Special:FilePath/Helenhayes32767v.jpg","sex_or_gender":"http://www.wikidata.org/entity/Q6581072","sex_or_genderLabel":"female"},{"human":"http://www.wikidata.org/entity/Q248837","humanLabel":"Susan Hayward","image":"http://commons.wikimedia.org/wiki/Special:FilePath/SusanHaywardinSmashUp.jpg","sex_or_gender":"http://www.wikidata.org/entity/Q6581072","sex_or_genderLabel":"female"},{"human":"http://www.wikidata.org/entity/Q253384","humanLabel":"Loretta Young","image":"http://commons.wikimedia.org/wiki/Special:FilePath/Loretta%20Young%20in%20She%20Had%20to%20Say%20Yes%20trailer.jpg","sex_or_gender":"http://www.wikidata.org/entity/Q6581072","sex_or_genderLabel":"female"}]